{"version":2,"kind":"Article","sha256":"495d05d3b33f1cfc78a5724c25306128d3588b17ebc4e8ee1bdc77e738a93e2c","slug":"about-edc-pangeo","location":"/pangeo/earthcode101/about_edc_pangeo.md","dependencies":[],"frontmatter":{"title":"EDC Pangeo Cloud Platform","content_includes_title":false,"license":{"content":{"id":"CC-BY-4.0","url":"https://creativecommons.org/licenses/by/4.0/","name":"Creative Commons Attribution 4.0 International","free":true,"CC":true},"code":{"id":"MIT","url":"https://opensource.org/licenses/MIT","name":"MIT License","free":true,"osi":true}},"github":"https://github.com/ESA-EarthCODE/tutorials","subject":"EarthCODE Tutorials","numbering":{"title":{"offset":2}},"source_url":"https://github.com/ESA-EarthCODE/tutorials/blob/main/pangeo/earthcode101/about_edc_pangeo.md","edit_url":"https://github.com/ESA-EarthCODE/tutorials/edit/main/pangeo/earthcode101/about_edc_pangeo.md","exports":[{"format":"md","filename":"about_edc_pangeo.md","url":"/tutorials/build/about_edc_pangeo-c3e0bbec63087e1b045a5e65a14ff7c4.md"}]},"mdast":{"type":"root","children":[{"type":"block","children":[{"type":"heading","depth":2,"position":{"start":{"line":3,"column":1},"end":{"line":3,"column":1}},"children":[{"type":"text","value":"About the Environment: Introducing the EDC Pangeo Cloud Platform","position":{"start":{"line":3,"column":1},"end":{"line":3,"column":1}},"key":"DbzyukrZsE"}],"identifier":"about-the-environment-introducing-the-edc-pangeo-cloud-platform","label":"About the Environment: Introducing the EDC Pangeo Cloud Platform","html_id":"about-the-environment-introducing-the-edc-pangeo-cloud-platform","implicit":true,"key":"dHlZDZnc8J"},{"type":"paragraph","position":{"start":{"line":5,"column":1},"end":{"line":5,"column":1}},"children":[{"type":"text","value":"You can now work with the Pangeo stack on the EDC EOxHub!","position":{"start":{"line":5,"column":1},"end":{"line":5,"column":1}},"key":"zxxUuXckTM"}],"key":"NYQXtZsCGt"},{"type":"paragraph","position":{"start":{"line":7,"column":1},"end":{"line":7,"column":1}},"children":[{"type":"strong","position":{"start":{"line":7,"column":1},"end":{"line":7,"column":1}},"children":[{"type":"text","value":"What is Pangeo?","position":{"start":{"line":7,"column":1},"end":{"line":7,"column":1}},"key":"yQ1XUgc0rm"}],"key":"a6My6hde1P"}],"key":"x8LXccibfQ"},{"type":"paragraph","position":{"start":{"line":9,"column":1},"end":{"line":9,"column":1}},"children":[{"type":"text","value":"Pangeo is a community-driven open-source ecosystem designed for scalable, Pythonic big data analysis. It brings a suite of powerful libraries that make working with large Earth observation and climate datasets easier and more interactive.","position":{"start":{"line":9,"column":1},"end":{"line":9,"column":1}},"key":"VTdNtM7phk"}],"key":"uG4tf2Z47e"},{"type":"paragraph","position":{"start":{"line":11,"column":1},"end":{"line":11,"column":1}},"children":[{"type":"strong","position":{"start":{"line":11,"column":1},"end":{"line":11,"column":1}},"children":[{"type":"text","value":"Key Tools in Pangeo","position":{"start":{"line":11,"column":1},"end":{"line":11,"column":1}},"key":"las0YFahKl"}],"key":"CRobNPxmJU"},{"type":"text","value":" that you will learn about today:","position":{"start":{"line":11,"column":1},"end":{"line":11,"column":1}},"key":"tViNUiFNZo"}],"key":"iJFAbEztyA"},{"type":"list","ordered":false,"spread":false,"position":{"start":{"line":12,"column":1},"end":{"line":17,"column":1}},"children":[{"type":"listItem","spread":true,"position":{"start":{"line":12,"column":1},"end":{"line":12,"column":1}},"children":[{"type":"paragraph","children":[{"type":"strong","position":{"start":{"line":12,"column":1},"end":{"line":12,"column":1}},"children":[{"type":"text","value":"Xarray","position":{"start":{"line":12,"column":1},"end":{"line":12,"column":1}},"key":"GTCzUb4PBH"}],"key":"HdBLrEsaqx"},{"type":"text","value":": Handles multi-dimensional labeled arrays (like NetCDF), with intuitive syntax that feels natural for Python users.","position":{"start":{"line":12,"column":1},"end":{"line":12,"column":1}},"key":"I7jYNt2MhG"}],"key":"RMAVY5NWSB"}],"key":"TfvgbJL74S"},{"type":"listItem","spread":true,"position":{"start":{"line":13,"column":1},"end":{"line":13,"column":1}},"children":[{"type":"paragraph","children":[{"type":"strong","position":{"start":{"line":13,"column":1},"end":{"line":13,"column":1}},"children":[{"type":"text","value":"STAC","position":{"start":{"line":13,"column":1},"end":{"line":13,"column":1}},"key":"SgLSQR0DRh"}],"key":"ckK3mJ2fl3"},{"type":"text","value":": Simplifies discovery and access to large Earth observation datasets with a consistent, JSON-based catalog standard.","position":{"start":{"line":13,"column":1},"end":{"line":13,"column":1}},"key":"GemahIFB7L"}],"key":"kUjYQBMNtO"}],"key":"OZE0CksbNn"},{"type":"listItem","spread":true,"position":{"start":{"line":14,"column":1},"end":{"line":14,"column":1}},"children":[{"type":"paragraph","children":[{"type":"strong","position":{"start":{"line":14,"column":1},"end":{"line":14,"column":1}},"children":[{"type":"text","value":"Dask","position":{"start":{"line":14,"column":1},"end":{"line":14,"column":1}},"key":"dUrh4AZA0q"}],"key":"Z6OLDiMekb"},{"type":"text","value":": Enables parallel and distributed computing, scaling analysis from laptops to powerful cloud clusters.","position":{"start":{"line":14,"column":1},"end":{"line":14,"column":1}},"key":"bEE6WtL3Xy"}],"key":"igdfG6PmxE"}],"key":"lCVzdRFabE"},{"type":"listItem","spread":true,"position":{"start":{"line":15,"column":1},"end":{"line":15,"column":1}},"children":[{"type":"paragraph","children":[{"type":"strong","position":{"start":{"line":15,"column":1},"end":{"line":15,"column":1}},"children":[{"type":"text","value":"Zarr","position":{"start":{"line":15,"column":1},"end":{"line":15,"column":1}},"key":"hJZaq2pIcc"}],"key":"FUNQHurYpX"},{"type":"text","value":": Provides efficient, cloud-native storage for chunked and compressed data, perfect for massive datasets.","position":{"start":{"line":15,"column":1},"end":{"line":15,"column":1}},"key":"QyuhQDDEqP"}],"key":"dpe2MMLgsh"}],"key":"Q1mI8KRI4o"},{"type":"listItem","spread":true,"position":{"start":{"line":16,"column":1},"end":{"line":17,"column":1}},"children":[{"type":"paragraph","children":[{"type":"strong","position":{"start":{"line":16,"column":1},"end":{"line":16,"column":1}},"children":[{"type":"text","value":"Jupyter","position":{"start":{"line":16,"column":1},"end":{"line":16,"column":1}},"key":"w93xqVtpia"}],"key":"OeLZ37sAoP"},{"type":"text","value":": Delivers an interactive, shareable environment for building and sharing workflows.","position":{"start":{"line":16,"column":1},"end":{"line":16,"column":1}},"key":"idybqFTtSO"}],"key":"D7hEioiuQZ"}],"key":"hziryWnrtI"}],"key":"nDuEwn4pfE"},{"type":"paragraph","position":{"start":{"line":18,"column":1},"end":{"line":18,"column":1}},"children":[{"type":"text","value":"These tools work together embracing the Pythonic way of data science and enabling intuitive exploration and high-performance analysis in the cloud.","position":{"start":{"line":18,"column":1},"end":{"line":18,"column":1}},"key":"SpUGF9dS0e"}],"key":"S6eagKpuIq"},{"type":"paragraph","position":{"start":{"line":21,"column":1},"end":{"line":22,"column":1}},"children":[{"type":"strong","position":{"start":{"line":21,"column":1},"end":{"line":21,"column":1}},"children":[{"type":"text","value":"Euro Data Cube (EDC)","position":{"start":{"line":21,"column":1},"end":{"line":21,"column":1}},"key":"APB65M1COE"}],"key":"FIWiVqkFrb"},{"type":"break","position":{"start":{"line":21,"column":1},"end":{"line":21,"column":1}},"key":"BzmVUkihkn"},{"type":"text","value":"A cloud platform for Earth observation data access and analysis, featuring a rich data catalog (Sentinel, Landsat, Copernicus, etc.), cloud-native analytics, and collaborative sharing tools for environmental, disaster, and climate applications. See more details at: ","position":{"start":{"line":21,"column":1},"end":{"line":21,"column":1}},"key":"zkvrHAmeg7"},{"type":"link","url":"https://eurodatacube.com","position":{"start":{"line":21,"column":1},"end":{"line":21,"column":1}},"children":[{"type":"text","value":"eurodatacube.com","position":{"start":{"line":21,"column":1},"end":{"line":21,"column":1}},"key":"Ls47JWekHT"}],"urlSource":"https://eurodatacube.com","key":"BOVDr2Xq6Y"}],"key":"TxE8Oq7SUz"},{"type":"paragraph","position":{"start":{"line":25,"column":1},"end":{"line":26,"column":1}},"children":[{"type":"strong","position":{"start":{"line":25,"column":1},"end":{"line":25,"column":1}},"children":[{"type":"text","value":"EDC EOxHub Workspace Offering","position":{"start":{"line":25,"column":1},"end":{"line":25,"column":1}},"key":"EeyZBd6yKR"}],"key":"i33ZHYZmyN"},{"type":"break","position":{"start":{"line":25,"column":1},"end":{"line":25,"column":1}},"key":"XqIWrt1bVF"},{"type":"text","value":"The EDC EOxHub Workspaces provide managed JupyterLab environments with curated images for EO projects. They offer customizable computing resources, persistent storage, and fast network connections. Users can run notebooks and applications, with fair use limits based on resource consumption. See more details at: ","position":{"start":{"line":25,"column":1},"end":{"line":25,"column":1}},"key":"UCSnDgnSEq"},{"type":"link","url":"https://eurodatacube.com/marketplace/infra/edc_eoxhub_workspace","position":{"start":{"line":25,"column":1},"end":{"line":25,"column":1}},"children":[{"type":"text","value":"EOxHub Workspace","position":{"start":{"line":25,"column":1},"end":{"line":25,"column":1}},"key":"EqibihR8bX"}],"urlSource":"https://eurodatacube.com/marketplace/infra/edc_eoxhub_workspace","key":"ym42TeFpTv"}],"key":"UZNdcRWphk"},{"type":"admonition","kind":"hint","children":[{"type":"admonitionTitle","children":[{"type":"text","value":"Network of Resources Sponsorship!","position":{"start":{"line":29,"column":1},"end":{"line":29,"column":1}},"key":"u7HyApWugN"}],"key":"EaEkEpTYis"},{"type":"paragraph","position":{"start":{"line":31,"column":1},"end":{"line":31,"column":1}},"children":[{"type":"text","value":"NoR provides non-commercial and commercial users with a unique environment to discover European cloud services and their estimate costs for Earth Observation exploitation. ESA offers sponsorship to eligible entities to cover the costs of trying out the various services.","position":{"start":{"line":31,"column":1},"end":{"line":31,"column":1}},"key":"nqZ3IGi8g7"}],"key":"V4OXa4usuB"},{"type":"paragraph","position":{"start":{"line":33,"column":1},"end":{"line":33,"column":1}},"children":[{"type":"strong","position":{"start":{"line":33,"column":1},"end":{"line":33,"column":1}},"children":[{"type":"text","value":"You can apply to sponsor your project’s compute and data access at: ","position":{"start":{"line":33,"column":1},"end":{"line":33,"column":1}},"key":"Za2qM6tMVk"},{"type":"link","url":"https://nor-discover.org/","position":{"start":{"line":33,"column":1},"end":{"line":33,"column":1}},"children":[{"type":"text","value":"https://​nor​-discover​.org/","position":{"start":{"line":33,"column":1},"end":{"line":33,"column":1}},"key":"Wa9M3ZBYD4"}],"urlSource":"https://nor-discover.org/","key":"W2sC5gfezX"}],"key":"AqPCtnlwp6"}],"key":"Z0r7mnoPpJ"}],"key":"NCz65SwR09"}],"key":"QOMFO2YLl9"}],"key":"yC6RLNpAwP"},"references":{"cite":{"order":[],"data":{}}},"footer":{"navigation":{"prev":{"title":"EarthCODE and Pangeo","url":"/earthcode101","group":"EarthCODE Tutorials"},"next":{"title":"Accessing EarthCODE Data","url":"/stac-and-data-access","group":"EarthCODE Tutorials"}}},"domain":"http://localhost:3000"}